Metadata-Version: 2.1
Name: odoo14-addon-sale_order_note_template
Version: 14.0.1.0.1
Summary: Add sale orders terms and conditions template that can be used to quickly fullfill sale order terms and conditions
Home-page: https://github.com/OCA/sale-workflow
Author: Pierre Verkest,Odoo Community Association (OCA)
Author-email: support@odoo-community.org
License: AGPL-3
Classifier: Programming Language :: Python
Classifier: Framework :: Odoo
Classifier: Framework :: Odoo :: 14.0
Classifier: License :: OSI Approved :: GNU Affero General Public License v3
Requires-Python: >=3.6
Requires-Dist: odoo<14.1dev,>=14.0a
